odoo10_addon_sale_order_import-10.0.1.0.0.99.dev14-nspkg.pth
odoo/addons/sale_order_import/README.rst
odoo/addons/sale_order_import/__init__.py
odoo/addons/sale_order_import/__manifest__.py
odoo/addons/sale_order_import/i18n/es.po
odoo/addons/sale_order_import/i18n/fr.po
odoo/addons/sale_order_import/i18n/it.po
odoo/addons/sale_order_import/i18n/sale_order_import.pot
odoo/addons/sale_order_import/models/__init__.py
odoo/addons/sale_order_import/models/sale.py
odoo/addons/sale_order_import/static/description/icon.png
odoo/addons/sale_order_import/tests/__init__.py
odoo/addons/sale_order_import/tests/test_order_import.py
odoo/addons/sale_order_import/wizard/__init__.py
odoo/addons/sale_order_import/wizard/sale_order_import.py
odoo/addons/sale_order_import/wizard/sale_order_import_view.xml
odoo10_addon_sale_order_import-10.0.1.0.0.99.dev14.dist-info/METADATA
odoo10_addon_sale_order_import-10.0.1.0.0.99.dev14.dist-info/WHEEL
odoo10_addon_sale_order_import-10.0.1.0.0.99.dev14.dist-info/namespace_packages.txt
odoo10_addon_sale_order_import-10.0.1.0.0.99.dev14.dist-info/top_level.txt
odoo10_addon_sale_order_import-10.0.1.0.0.99.dev14.dist-info/RECORD
